{"id":"8a26e12f-7af4-8eca-d4ad-fe8bec3660d7","name":"Content Launch","timestamp":1393807705082,"order":["b76a8255-4f21-428e-16a6-22b39b9b46e2","a158ad35-9600-3eea-c2ce-b4d69566863d","b633100b-b35f-5790-4b49-44db1a370d80","34768211-9441-de10-fd68-60809a40f705","c93e3e33-e2c4-523b-f5d6-ef0807328161","0a96f766-9827-d1b2-7894-5d55d802202d","d637dc5e-3736-8250-25e2-c1e5455886e4","d9e4137f-df0c-e773-98db-d9c261e8f0b8","c2e18bd9-c50e-0b53-7aba-4adf19ba5eae","1d7db26b-9a3b-4994-f01b-4ed889961c49","7ced6cfe-eea3-172b-af75-d4311544a906","31137a84-b203-7f3d-2ac7-7e372d52a233","c7dc1b90-8774-0cd2-8ce4-da958cbd57e2","0ccdd540-befc-cd95-8a06-d9772cfad912","42fbb340-2c14-718e-58ca-1f2240cda29c","9d0cbe98-b228-18c5-96ba-75167334e181","99008259-2ea0-0b4a-03e9-8eae444412ca","13e12a08-d15b-82fb-57e2-2cb5f4b70284"],"requests":[{"collectionId":"8a26e12f-7af4-8eca-d4ad-fe8bec3660d7","id":"0a96f766-9827-d1b2-7894-5d55d802202d","name":"Account: Get account users","description":"","url":"{{baseurl}}/api/account/{{account_id}}/users","method":"GET","headers":"","data":[{"key":"user_id","value":"{{user_id}}","type":"text"}],"dataMode":"params","timestamp":0,"version":2,"time":1393990818456},{"collectionId":"8a26e12f-7af4-8eca-d4ad-fe8bec3660d7","id":"0ccdd540-befc-cd95-8a06-d9772cfad912","name":"Role: Get roles","description":"","url":"{{baseurl}}/api/role","method":"GET","headers":"","data":[],"dataMode":"params","timestamp":0,"version":2,"time":1393990942038},{"collectionId":"8a26e12f-7af4-8eca-d4ad-fe8bec3660d7","id":"13e12a08-d15b-82fb-57e2-2cb5f4b70284","name":"Role: Delete a role","description":"","url":"{{baseurl}}/api/role/{role_id}","method":"DELETE","headers":"","data":[],"dataMode":"params","timestamp":0,"version":2,"time":1393990981889},{"collectionId":"8a26e12f-7af4-8eca-d4ad-fe8bec3660d7","id":"1d7db26b-9a3b-4994-f01b-4ed889961c49","name":"User: Get users","description":"","url":"{{baseurl}}/api/user","method":"GET","headers":"","data":[{"key":"email","value":"","type":"text"},{"key":"password","value":"","type":"text"}],"dataMode":"params","timestamp":0,"version":2,"time":1393990882222},{"collectionId":"8a26e12f-7af4-8eca-d4ad-fe8bec3660d7","id":"31137a84-b203-7f3d-2ac7-7e372d52a233","name":"User: Update a user","description":"","url":"{{baseurl}}/api/user/{{user_id}}","method":"PUT","headers":"","data":[{"key":"email","value":"","type":"text"},{"key":"password","value":"","type":"text"},{"key":"password_confirmation","value":"","type":"text"},{"key":"confirmed","value":"1","type":"text"},{"key":"first_name","value":"","type":"text"},{"key":"last_name","value":"","type":"text"}],"dataMode":"params","timestamp":0,"version":2,"time":1393990913887},{"collectionId":"8a26e12f-7af4-8eca-d4ad-fe8bec3660d7","id":"34768211-9441-de10-fd68-60809a40f705","name":"Account: Delete an account","description":"","url":"{{baseurl}}/api/account/{account_id}","method":"DELETE","headers":"","data":[],"dataMode":"params","timestamp":0,"version":2,"time":1393990795961},{"collectionId":"8a26e12f-7af4-8eca-d4ad-fe8bec3660d7","id":"42fbb340-2c14-718e-58ca-1f2240cda29c","name":"Role: Create new role","description":"","url":"{{baseurl}}/api/role","method":"POST","headers":"","data":[{"key":"name","value":"","type":"text"}],"dataMode":"params","timestamp":0,"version":2,"time":1393990954730},{"collectionId":"8a26e12f-7af4-8eca-d4ad-fe8bec3660d7","id":"7ced6cfe-eea3-172b-af75-d4311544a906","name":"User: Create a new user","description":"","url":"{{baseurl}}/api/user","method":"POST","headers":"","data":[{"key":"email","value":"","type":"text"},{"key":"password","value":"","type":"text"},{"key":"password_confirmation","value":"","type":"text"},{"key":"confirmed","value":"1","type":"text"},{"key":"first_name","value":"","type":"text"},{"key":"last_name","value":"","type":"text"}],"dataMode":"params","timestamp":0,"version":2,"time":1393990898669},{"collectionId":"8a26e12f-7af4-8eca-d4ad-fe8bec3660d7","id":"99008259-2ea0-0b4a-03e9-8eae444412ca","name":"Role: Update a role","description":"","url":"{{baseurl}}/api/role/{role_id}","method":"PUT","headers":"","data":[{"key":"name","value":"","type":"text"}],"dataMode":"params","timestamp":0,"version":2,"time":1393990973985},{"collectionId":"8a26e12f-7af4-8eca-d4ad-fe8bec3660d7","id":"9d0cbe98-b228-18c5-96ba-75167334e181","name":"Role: Get a role","description":"","url":"{{baseurl}}/api/role/{role_id}","method":"GET","headers":"","data":[{"key":"name","value":"","type":"text"}],"dataMode":"params","timestamp":0,"version":2,"time":1393990963520},{"collectionId":"8a26e12f-7af4-8eca-d4ad-fe8bec3660d7","id":"a158ad35-9600-3eea-c2ce-b4d69566863d","name":"Account: Create new account","description":"","url":"{{baseurl}}/api/account","method":"POST","headers":"","data":[{"key":"title","value":"","type":"text"},{"key":"active","value":"","type":"text"}],"dataMode":"params","timestamp":0,"version":2,"time":1393990769285},{"collectionId":"8a26e12f-7af4-8eca-d4ad-fe8bec3660d7","id":"b633100b-b35f-5790-4b49-44db1a370d80","name":"Account: Update an account","description":"","url":"{{baseurl}}/api/account/{account_id}","method":"PUT","headers":"","data":[{"key":"title","value":"","type":"text"},{"key":"active","value":"","type":"text"}],"dataMode":"params","timestamp":0,"version":2,"time":1393990786320},{"collectionId":"8a26e12f-7af4-8eca-d4ad-fe8bec3660d7","id":"b76a8255-4f21-428e-16a6-22b39b9b46e2","name":"Account: Get accounts","description":"","url":"{{baseurl}}/api/account","method":"GET","headers":"","data":[{"key":"title","value":"","type":"text"},{"key":"active","value":"","type":"text"}],"dataMode":"params","timestamp":0,"version":2,"time":1393990778321},{"collectionId":"8a26e12f-7af4-8eca-d4ad-fe8bec3660d7","id":"c2e18bd9-c50e-0b53-7aba-4adf19ba5eae","name":"Auth: Logout","description":"","url":"{{baseurl}}/api/auth/logout","method":"GET","headers":"","data":[{"key":"email","value":"","type":"text"},{"key":"password","value":"","type":"text"}],"dataMode":"params","timestamp":0,"version":2,"time":1393990851066},{"collectionId":"8a26e12f-7af4-8eca-d4ad-fe8bec3660d7","id":"c7dc1b90-8774-0cd2-8ce4-da958cbd57e2","name":"User: Delete a user","description":"","url":"{{baseurl}}/api/user/{{user_id}}","method":"DELETE","headers":"","data":[],"dataMode":"params","timestamp":0,"version":2,"time":1393990929517},{"collectionId":"8a26e12f-7af4-8eca-d4ad-fe8bec3660d7","id":"c93e3e33-e2c4-523b-f5d6-ef0807328161","name":"Account: Add user to account","description":"","url":"{{baseurl}}/api/account/{{account_id}}/add_user","method":"POST","headers":"","data":[{"key":"user_id","value":"{{user_id}}","type":"text"}],"dataMode":"params","timestamp":0,"version":2,"time":1393990738539},{"collectionId":"8a26e12f-7af4-8eca-d4ad-fe8bec3660d7","id":"d637dc5e-3736-8250-25e2-c1e5455886e4","name":"Auth: Get current user","description":"","url":"{{baseurl}}/api/auth","method":"GET","headers":"","data":[{"key":"user_id","value":"{{user_id}}","type":"text"}],"dataMode":"params","timestamp":0,"version":2,"time":1393990832216},{"collectionId":"8a26e12f-7af4-8eca-d4ad-fe8bec3660d7","id":"d9e4137f-df0c-e773-98db-d9c261e8f0b8","name":"Auth: Login","description":"","url":"{{baseurl}}/api/auth","method":"POST","headers":"","data":[{"key":"email","value":"","type":"text"},{"key":"password","value":"","type":"text"}],"dataMode":"params","timestamp":0,"version":2,"time":1393990841087}]}
